macuitest/__init__.py
macuitest/config/__init__.py
macuitest/config/colors.py
macuitest/config/constants.py
macuitest/config/country_codes.py
macuitest/lib/__init__.py
macuitest/lib/core.py
macuitest/lib/applescript_lib/__init__.py
macuitest/lib/applescript_lib/aeconverter.py
macuitest/lib/applescript_lib/aeobjects.py
macuitest/lib/applescript_lib/applescript_wrapper.py
macuitest/lib/apps/__init__.py
macuitest/lib/apps/application.py
macuitest/lib/apps/browser.py
macuitest/lib/elements/__init__.py
macuitest/lib/elements/applescript_element.py
macuitest/lib/elements/native_element.py
macuitest/lib/elements/ui_element.py
macuitest/lib/elements/controllers/__init__.py
macuitest/lib/elements/controllers/keyboard_controller.py
macuitest/lib/elements/controllers/keyboard_mappings.py
macuitest/lib/elements/controllers/mouse.py
macuitest/lib/elements/controllers/mouse_controller.py
macuitest/lib/elements/native/__init__.py
macuitest/lib/elements/native/calls.py
macuitest/lib/elements/native/converter.py
macuitest/lib/elements/native/native_ui_element.py
macuitest/lib/elements/ui/__init__.py
macuitest/lib/elements/ui/monitor.py
macuitest/lib/elements/ui/ocr_manager.py
macuitest/lib/elements/ui/screen_recorder.py
macuitest/lib/elements/ui/screenshot_path_builder.py
macuitest/lib/operating_system/__init__.py
macuitest/lib/operating_system/color_meter.py
macuitest/lib/operating_system/crash_reporter.py
macuitest/lib/operating_system/db_manager.py
macuitest/lib/operating_system/defaults.py
macuitest/lib/operating_system/disk_util.py
macuitest/lib/operating_system/env.py
macuitest/lib/operating_system/file_manager.py
macuitest/lib/operating_system/hosts.py
macuitest/lib/operating_system/login_window.py
macuitest/lib/operating_system/macos.py
macuitest/lib/operating_system/memory_manager.py
macuitest/lib/operating_system/networking.py
macuitest/lib/operating_system/plist_helper.py
macuitest/lib/operating_system/security_manager.py
macuitest/lib/operating_system/service_manager.py
macuitest-0.7.43.dist-info/LICENSE
macuitest-0.7.43.dist-info/METADATA
macuitest-0.7.43.dist-info/WHEEL
macuitest-0.7.43.dist-info/top_level.txt
macuitest-0.7.43.dist-info/RECORD
