Metadata-Version: 2.1
Name: macuitest
Version: 0.7.43
Summary: A simple UI testing framework for macOS
Home-page: https://github.com/andriykislitsyn/macuitest
Author: Andrii Kislitsyn
Author-email: andriikislitsyn@gmail.com
License: MIT
Keywords: macOS,Testing,E2E,UI,Automator,Accessibility
Platform: osx
Classifier: Topic :: Software Development :: Testing
Classifier: Topic :: Software Development :: Quality Assurance
Classifier: Topic :: Education :: Testing
Classifier: Operating System :: MacOS
Classifier: Programming Language :: Python :: 3 :: Only
Classifier: Programming Language :: Python :: 3.7
Classifier: Programming Language :: Python :: 3.8
Classifier: Programming Language :: Python :: 3.9
Requires-Python: >=3.7.0
License-File: LICENSE
Requires-Dist: biplist (>=1.0.3)
Requires-Dist: opencv-python (>=4.5.3)
Requires-Dist: pyobjc-framework-ApplicationServices (>=7.3)
Requires-Dist: pyobjc-framework-AVFoundation (>=7.3)
Requires-Dist: pyobjc-framework-Cocoa (>=7.3)
Requires-Dist: pyobjc-framework-CoreMedia (>=7.3)
Requires-Dist: pyobjc-framework-CoreText (>=7.3)
Requires-Dist: pyobjc-framework-Quartz (>=7.3)
Requires-Dist: pytesseract (>=0.3)
Provides-Extra: testing
Requires-Dist: pytest ; extra == 'testing'
Requires-Dist: black ; extra == 'testing'
Requires-Dist: flake8 ; extra == 'testing'
Requires-Dist: isort ; extra == 'testing'
Requires-Dist: mypy ; extra == 'testing'
Requires-Dist: tox ; extra == 'testing'
